braille_progress/__init__.py
braille_progress/braille.py
braille_progress/cli.py
braille_progress/errorfmt.py
braille_progress/layout.py
braille_progress/message.py
braille_progress/model.py
braille_progress/progress.py
braille_progress/py.typed
braille_progress/queue.py
braille_progress/ratio.py
braille_progress/render.py
braille_progress/stats.py
braille_progress/style.py
braille_progress/terminal.py
braille_progress/theme.py
braille_progress/ui.py
braille_progress/util.py
braille_progress/widgets.py
bprogress-1.0.0.dist-info/METADATA
bprogress-1.0.0.dist-info/WHEEL
bprogress-1.0.0.dist-info/licenses/LICENSE
bprogress-1.0.0.dist-info/RECORD
