Metadata-Version: 2.4
Name: bprogress
Version: 1.0.0
Summary: Braille-based multi progress bars with ANSI colors (docker-compose style)
Project-URL: Homepage, https://github.com/kibalab/braille-progress
Project-URL: Repository, https://github.com/kibalab/braille-progress
Author-email: Your Name <you@example.com>
License: MIT License
License-File: LICENSE
Keywords: ansi,braille,cli,progress,terminal
Classifier: Environment :: Console
Classifier: License :: OSI Approved :: MIT License
Classifier: Programming Language :: Python :: 3
Classifier: Topic :: Utilities
Requires-Python: >=3.8
